[
  {
    "id": 1,
    "countryName": "Japan",
    "capital": "Tokyo",
    "population": 125800000,
    "interestingFact": "Japan is made up of over 6,800 islands."
  },
  {
    "id": 2,
    "countryName": "Canada",
    "capital": "Ottawa",
    "population": 38930000,
    "interestingFact": "Canada has the longest coastline in the world."
  },
  {
    "id": 3,
    "countryName": "Egypt",
    "capital": "Cairo",
    "population": 104258327,
    "interestingFact": "The Pyramids of Giza are the only surviving Wonder of the Ancient World."
  },
  {
    "id": 4,
    "countryName": "Australia",
    "capital": "Canberra",
    "population": 25960000,
    "interestingFact": "Australia is home to the world's largest coral reef system, the Great Barrier Reef."
  },
  {
    "id": 5,
    "countryName": "Brazil",
    "capital": "Brasília",
    "population": 215300000,
    "interestingFact": "Brazil is home to about 60% of the Amazon Rainforest."
  },
  {
    "id": 6,
    "countryName": "India",
    "capital": "New Delhi",
    "population": 1417173173,
    "interestingFact": "India is the world’s largest democracy by population."
  },
  {
    "id": 7,
    "countryName": "Russia",
    "capital": "Moscow",
    "population": 146400000,
    "interestingFact": "Russia is the largest country in the world by land area."
  },
  {
    "id": 8,
    "countryName": "Italy",
    "capital": "Rome",
    "population": 58850000,
    "interestingFact": "Rome is home to the smallest country in the world, Vatican City."
  },
  {
    "id": 9,
    "countryName": "China",
    "capital": "Beijing",
    "population": 1425671352,
    "interestingFact": "China has the world’s largest high-speed rail network."
  },
  {
    "id": 10,
    "countryName": "South Africa",
    "capital": "Pretoria",
    "population": 60900000,
    "interestingFact": "South Africa has three capital cities: Pretoria, Cape Town, and Bloemfontein."
  }
]
